Workbook

Sheet Campaign Root KW
A1: Category Name
A2: 0-Gen
A3: 1-Gift
A4: 2-Accessories
A5: 3-Training Aids
A6: 4-Putter
A7: 5-Swing
A8: 6-Mirror
A9: 7-Putting
A10: 8-Practice
A11: 9-Trainer
A12: 10-Alignment

Sheet Campaign Naming, Bids & Targets
A1: Action | B1: Product Name | C1: Campaign Type | D1: Landing Page | E1: KW or PT | F1: Match Type | G1: Root KW | H1: Campaign Goal | I1: Campaign Name | J1: Profile | K1: Daily Budget | L1: Date Range | M1: Targeting Type | N1: Brand | O1: Goals | P1: Bidding Strategy | Q1: Placement Bid Adjustment (Top of Search) | R1: Placement Bid Adjustment (Product Pages) | S1: Placement Bid Adjustment (Rest of Search) | T1: Campaign Tag | U1: Portfolio | V1: Targeting Type | W1: Ad Group Name | X1: Landing Page | Y1: Cost Control | Z1: Default Bid | AA1: ASIN/SKU | AB1: Targets | AC1: Negative Phrase | AD1: Negative Exact | AE1: Negative PAT | AF1: Headline | AG1: Video Filename | AH1: Placement Modifier | AI1: ASP | AJ1: ACoS Target | AK1: Conversion Rate | AL1: Starting Bid | AM1: Repurpose Campaign | AN1: Helper

Sheet Sheet1
A1: SPM | SKW | Ex.
A2: SPM | MKW | Ex.
A3: SPM | MKW | Br.M
A4: SPM | MKW | Br.
A5: SPA
A6: SPM | CT
A7: SPM | PT | Ex.
A8: SPM | PT | Exp.
A9: SPM | STPP
A10: SB | PC-Store | MKW | Ex.
A11: SB | PC-Store | MKW | Br.M
A12: SB | PC-Store | MKW | Ph.
... A20: SDI | PP | PT | Ex.

Sheet PAT
D1: ="www.amazon.com/dp/"&B1 | E1: {=IFERROR(_xludf.XLOOKUP(B1,'Search Term Report'!A:A,'Search Term Report'!S:S),0)} | F1: {=IFERROR(_xludf.XLOOKUP(B1,'Search Term Report'!A:A,'Search Term Report'!U:U),0)} | G1: {=IFERROR(_xludf.XLOOKUP(B1,'Search Term Report'!A:A,'Search Term Report'!Q:Q),0)} | H1: {=IFERROR(_xludf.XLOOKUP(B1,'Search Term Report'!A:A,'Search Term Report'!R:R),0)} | K1: Mirror | L1: {=IFERROR(_xludf.XLOOKUP(K1&"-PT-Ex.-"&$J1,'Campaign Naming, Bids & Targets'!$AN:$AN,'Campaign Naming, Bids & Targets'!$I:$I),"n/a")} | M1: {=IFERROR(_xludf.XLOOKUP(J1,S:S,T:T),"")} | N1: 24.95 | O1: 0.25 | P1: =H1 | Q1: =ROUND((N1*O1*P1)/(1+M1),2)
A2: Source | B2: Search Term | C2: Title | D2: URL | E2: Sum of 7 Day Total Orders (#) | F2: Sum of $ CPC | G2: Sum of % ACoS | H2: Conversion Rate | I2: Matching Whoosh Product | J2: ASIN Cat Type | K2: Product Name 1 | L2: Campaign Name 1 | M2: Placement Modifier 1 | N2: ASP 1 | O2: ACoS Target 1 | P2: Conversion Rate 1 | Q2: Starting Bid 1 | S2: Root PAT | T2: Placement Bid Adjustment (Product Pages)

Sheet Semantics
O1: SKW | Q1: {=IFERROR(_xludf.XLOOKUP(O1&"-"&$L1&"-"&$M1&"-"&$A1,'Campaign Naming, Bids & Targets'!$AN:$AN,'Campaign Naming, Bids & Targets'!$I:$I),"n/a")} | R1: 0.25 | T1: 0.25 | U1: =ROUND((G1*S1*T1)/(1+R1),2)
C2: {=IFERROR(_xludf.XLOOKUP(A2,'Product Opportunity Explorer'!C:C,'Product Opportunity Explorer'!P:P),IFERROR(_xludf.XLOOKUP(A2,'SQP Report B0DQV3BZD7'!A:A,'SQP Report B0DQV3BZD7'!D:D),IFERROR(_xludf.XLOOKUP(A2,'[1]SQP Report B0DQV56XC5'!A:A,'[1]SQP Report B0DQV56XC5'!D:D),IFERROR(_xludf.XLOOKUP(A2,'Helium10 Reverse ASIN Search'!A:A,'Helium10 Reverse ASIN Search'!H:H),0))))} | D2: {=IFERROR(_xludf.XLOOKUP(A2,'Search Term Report'!A:A,'Search Term Report'!U:U),0)} | E2: {=IFERROR(_xludf.XLOOKUP(A2,'Search Term Report'!A:A,'Search Term Report'!S:S),0)} | F2: {=IFERROR(_xludf.XLOOKUP(A2,'Search Term Report'!A:A,'Search Term Report'!Q:Q),0)} | G2: {=IFERROR( _xludf.XLOOKUP(A2,'Search Term Report'!A:A,'Search Term Report'!R:R), IFERROR( _xludf.XLOOKUP(A2,'Helium10 Reverse ASIN Search'!A:A,'Helium10 Reverse ASIN Search'!C:C), 0 )% )} | I2: < 3.19 | J2: > 5.67 | O2: MKW | P2: Mirror | Q2: {=IFERROR(_xludf.XLOOKUP(O2&"-"&$L2&"-"&$M2&"-"&$K2,'Campaign Naming, Bids & Targets'!$AN:$AN,'Campaign Naming, Bids & Targets'!$I:$I),"n/a")} | R2: 0.1 | S2: 24.95 | T2: 0.2
A3: Keyword | B3: Source | C3: Search Volume | D3: Sum of 7 Day Total Orders (#) | E3: Sum of $ CPC | F3: Sum of % ACoS | G3: Conversion Rate | H3: Organic Rank | I3: Impression Share | J3: CTR | K3: Root KW | M3: KW Vol. | N3: Match Type | O3: Broad KW List | P3: Product Name | Q3: Campaign Name 1 | R3: Placement Modifier 1 | S3: ASP 1 | T3: ACoS Target 1 | U3: Starting Bid 1

Sheet ASIN List
D1: =B1&"/"&A1 | E1: =SUMIFS(Q:Q,L:L,B1) | F1: =SUMIFS(R:R,L:L,B1) | G1: =SUMIFS(S:S,L:L,B1) | L1: CTR Data
A2: seller-sku | B2: asin1 | C2: item-name | D2: ASIN/SKU | E2: Impressions | F2: Clicks | G2: CTR | H2: Rank | L2: ASIN | M2: SKU | N2: Title | O2: state | P2: Profile Name | Q2: Impression | R2: Click | S2: CTR | T2: Spend | U2: CPC | V2: Sales | W2: Orders | Y2: ACOS | Z2: Price | AA2: ASP

Sheet Master Keyword List
B2: 🎯Single Keyword Campaigns | C2: Category | D2: Search Volume 30 Days | E2: 🔎 "Root 1" KWs - car | F2: Search Volume 30 Days | G2: 🔎 "Root 2" KWs - computer | H2: Search Volume 30 Days | I2: 🔎 "Root 3" KWs - gen | J2: Search Volume 30 Days | K2: 🔎 "Root 4" KWs - phone | L2: Search Volume 30 Days | M2: 🔎 "Root 5" KWs - tablet | N2: Search Volume 30 Days | O2: 🔎 "Root 5" KWs - TV | P2: Search Volume 30 Days | R2: Helium10 KWs (Reverse ASIN) | S2: Search Volume 30 Days | T2: Product Opportunity Explorer KWs | U2: Search Volume 30 Days | V2: Brand Analytics Top Searched | W2: Search Volume 30 Days | X2: Search Term Report KWs | Y2: Orders | Z2: CPC | AA2: ACOS | AC2: Search Term Report ASINs | AD2: Matching Product | AE2: Orders | AF2: CPC | AG2: ACOS | AI2: Search Query Performance KWs | AJ2: Search Volume 30 Days | AL2: 🛡️Own Branded KWs | AM2: 🛡️Own Branded Searches | AN2: Search Volume 30 Days | AP2: 🛡️Competitor KWs | AQ2: 🛡️Competitor Searches | AR2: Search Volume 30 Days | AT2: 🇪🇸 Spanish KWs | AU2: Search Volume 30 Days | AW2: 🔍 Misspellings | AX2: 🔍 Misspellings Brand | AY2: Search Volume 30 Days | BA2: ⛔️Negate Words | BB2: ⛔️Negate Brands | BD2: Own Brand ASINs | BE2: Main Competitor ASINs | BF2: Lower Rated ASINs | BG2: Higher Priced ASINs | BH2: Bestselling ASINs | BI2: Harvested ASINs | BK2: 🫴🏻 Catch-All | BM2: 🗄️Categories | BN2: Search Volume | BO2: 👥Audiences

Sheet Top Competitors
D2: Main Competitors
D3: Identifying and evaluating the main competitors helps to better understand the keyword landscape of a product, and allows running a reverse ASIN search to identify the keywords with the highest relevance to a product. Data can most easily be exported using Helium10's XRay chrome extension.
D4: Your Product | E4: Competitor 1 | F4: Competitor 2 | G4: Competitor 3 | H4: Competitor 4 | I4: Competitor 5 | J4: Competitor 6 | K4: Competitor 7 | L4: Competitor 8 | M4: Competitor 9 | N4: Competitor 10
B5: Product Information | C5: Main Image | E5: =IFERROR(__xludf.DUMMYFUNCTION("SINGLE(IMAGE(E6))"),"") | F5: =IFERROR(__xludf.DUMMYFUNCTION("SINGLE(IMAGE(F6))"),"") | G5: =IFERROR(__xludf.DUMMYFUNCTION("SINGLE(IMAGE(G6))"),"") | H5: =IFERROR(__xludf.DUMMYFUNCTION("SINGLE(IMAGE(H6))"),"") | I5: =IFERROR(__xludf.DUMMYFUNCTION("SINGLE(IMAGE(I6))"),"") | J5: =IFERROR(__xludf.DUMMYFUNCTION("SINGLE(IMAGE(J6))"),"") | K5: =IFERROR(__xludf.DUMMYFUNCTION("SINGLE(IMAGE(K6))"),"") | L5: =IFERROR(__xludf.DUMMYFUNCTION("SINGLE(IMAGE(L6))"),"") | M5: =IFERROR(__xludf.DUMMYFUNCTION("SINGLE(IMAGE(M6))"),"") | N5: =IFERROR(__xludf.DUMMYFUNCTION("SINGLE(IMAGE(N6))"),"")
C6: Image URL | E6: =IFERROR(__xludf.DUMMYFUNCTION("SINGLE(IMAGE(E7))"),"") | F6: =IFERROR(__xludf.DUMMYFUNCTION("SINGLE(IMAGE(F7))"),"") | G6: =IFERROR(__xludf.DUMMYFUNCTION("SINGLE(IMAGE(G7))"),"") | H6: =IFERROR(__xludf.DUMMYFUNCTION("SINGLE(IMAGE(H7))"),"") | I6: =IFERROR(__xludf.DUMMYFUNCTION("SINGLE(IMAGE(I7))"),"") | J6: =IFERROR(__xludf.DUMMYFUNCTION("SINGLE(IMAGE(J7))"),"") | K6: =IFERROR(__xludf.DUMMYFUNCTION("SINGLE(IMAGE(K7))"),"") | L6: =IFERROR(__xludf.DUMMYFUNCTION("SINGLE(IMAGE(L7))"),"") | M6: =IFERROR(__xludf.DUMMYFUNCTION("SINGLE(IMAGE(M7))"),"") | N6: =IFERROR(__xludf.DUMMYFUNCTION("SINGLE(IMAGE(N7))"),"")
C7: Amazon URL | E7: =IFERROR(__xludf.DUMMYFUNCTION("SINGLE(IMAGE(E8))"),"") | F7: =IFERROR(__xludf.DUMMYFUNCTION("SINGLE(IMAGE(F8))"),"") | G7: =IFERROR(__xludf.DUMMYFUNCTION("SINGLE(IMAGE(G8))"),"") | H7: =IFERROR(__xludf.DUMMYFUNCTION("SINGLE(IMAGE(H8))"),"") | I7: =IFERROR(__xludf.DUMMYFUNCTION("SINGLE(IMAGE(I8))"),"") | J7: =IFERROR(__xludf.DUMMYFUNCTION("SINGLE(IMAGE(J8))"),"") | K7: =IFERROR(__xludf.DUMMYFUNCTION("SINGLE(IMAGE(K8))"),"") | L7: =IFERROR(__xludf.DUMMYFUNCTION("SINGLE(IMAGE(L8))"),"") | M7: =IFERROR(__xludf.DUMMYFUNCTION("SINGLE(IMAGE(M8))"),"") | N7: =IFERROR(__xludf.DUMMYFUNCTION("SINGLE(IMAGE(N8))"),"")
C8: ASIN | E8: =IFERROR(__xludf.DUMMYFUNCTION("SINGLE(IMAGE(E9))"),"") | F8: =IFERROR(__xludf.DUMMYFUNCTION("SINGLE(IMAGE(F9))"),"") | G8: =IFERROR(__xludf.DUMMYFUNCTION("SINGLE(IMAGE(G9))"),"") | H8: =IFERROR(__xludf.DUMMYFUNCTION("SINGLE(IMAGE(H9))"),"") | I8: =IFERROR(__xludf.DUMMYFUNCTION("SINGLE(IMAGE(I9))"),"") | J8: =IFERROR(__xludf.DUMMYFUNCTION("SINGLE(IMAGE(J9))"),"") | K8: =IFERROR(__xludf.DUMMYFUNCTION("SINGLE(IMAGE(K9))"),"") | L8: =IFERROR(__xludf.DUMMYFUNCTION("SINGLE(IMAGE(L9))"),"") | M8: =IFERROR(__xludf.DUMMYFUNCTION("SINGLE(IMAGE(M9))"),"") | N8: =IFERROR(__xludf.DUMMYFUNCTION("SINGLE(IMAGE(N9))"),"")
C9: Brand Name | E9: =IFERROR(__xludf.DUMMYFUNCTION("SINGLE(IMAGE(E10))"),"") | F9: =IFERROR(__xludf.DUMMYFUNCTION("SINGLE(IMAGE(F10))"),"") | G9: =IFERROR(__xludf.DUMMYFUNCTION("SINGLE(IMAGE(G10))"),"") | H9: =IFERROR(__xludf.DUMMYFUNCTION("SINGLE(IMAGE(H10))"),"") | I9: =IFERROR(__xludf.DUMMYFUNCTION("SINGLE(IMAGE(I10))"),"") | J9: =IFERROR(__xludf.DUMMYFUNCTION("SINGLE(IMAGE(J10))"),"") | K9: =IFERROR(__xludf.DUMMYFUNCTION("SINGLE(IMAGE(K10))"),"") | L9: =IFERROR(__xludf.DUMMYFUNCTION("SINGLE(IMAGE(L10))"),"") | M9: =IFERROR(__xludf.DUMMYFUNCTION("SINGLE(IMAGE(M10))"),"") | N9: =IFERROR(__xludf.DUMMYFUNCTION("SINGLE(IMAGE(N10))"),"")
B10: Sales | C10: Price | E10: =IFERROR(__xludf.DUMMYFUNCTION("SINGLE(IMAGE(E11))"),"") | F10: =IFERROR(__xludf.DUMMYFUNCTION("SINGLE(IMAGE(F11))"),"") | G10: =IFERROR(__xludf.DUMMYFUNCTION("SINGLE(IMAGE(G11))"),"") | H10: =IFERROR(__xludf.DUMMYFUNCTION("SINGLE(IMAGE(H11))"),"") | I10: =IFERROR(__xludf.DUMMYFUNCTION("SINGLE(IMAGE(I11))"),"") | J10: =IFERROR(__xludf.DUMMYFUNCTION("SINGLE(IMAGE(J11))"),"") | K10: =IFERROR(__xludf.DUMMYFUNCTION("SINGLE(IMAGE(K11))"),"") | L10: =IFERROR(__xludf.DUMMYFUNCTION("SINGLE(IMAGE(L11))"),"") | M10: =IFERROR(__xludf.DUMMYFUNCTION("SINGLE(IMAGE(M11))"),"") | N10: =IFERROR(__xludf.DUMMYFUNCTION("SINGLE(IMAGE(N11))"),"")
C11: Sales (Monthly) | E11: =IFERROR(__xludf.DUMMYFUNCTION("SINGLE(IMAGE(E12))"),"") | F11: =IFERROR(__xludf.DUMMYFUNCTION("SINGLE(IMAGE(F12))"),"") | G11: =IFERROR(__xludf.DUMMYFUNCTION("SINGLE(IMAGE(G12))"),"") | H11: =IFERROR(__xludf.DUMMYFUNCTION("SINGLE(IMAGE(H12))"),"") | I11: =IFERROR(__xludf.DUMMYFUNCTION("SINGLE(IMAGE(I12))"),"") | J11: =IFERROR(__xludf.DUMMYFUNCTION("SINGLE(IMAGE(J12))"),"") | K11: =IFERROR(__xludf.DUMMYFUNCTION("SINGLE(IMAGE(K12))"),"") | L11: =IFERROR(__xludf.DUMMYFUNCTION("SINGLE(IMAGE(L12))"),"") | M11: =IFERROR(__xludf.DUMMYFUNCTION("SINGLE(IMAGE(M12))"),"") | N11: =IFERROR(__xludf.DUMMYFUNCTION("SINGLE(IMAGE(N12))"),"")
C12: Revenue (Monthly) | E12: =IFERROR(__xludf.DUMMYFUNCTION("SINGLE(IMAGE(E13))"),"") | F12: =IFERROR(__xludf.DUMMYFUNCTION("SINGLE(IMAGE(F13))"),"") | G12: =IFERROR(__xludf.DUMMYFUNCTION("SINGLE(IMAGE(G13))"),"") | H12: =IFERROR(__xludf.DUMMYFUNCTION("SINGLE(IMAGE(H13))"),"") | I12: =IFERROR(__xludf.DUMMYFUNCTION("SINGLE(IMAGE(I13))"),"") | J12: =IFERROR(__xludf.DUMMYFUNCTION("SINGLE(IMAGE(J13))"),"") | K12: =IFERROR(__xludf.DUMMYFUNCTION("SINGLE(IMAGE(K13))"),"") | L12: =IFERROR(__xludf.DUMMYFUNCTION("SINGLE(IMAGE(L13))"),"") | M12: =IFERROR(__xludf.DUMMYFUNCTION("SINGLE(IMAGE(M13))"),"") | N12: =IFERROR(__xludf.DUMMYFUNCTION("SINGLE(IMAGE(N13))"),"")
B13: Reviews | C13: Average Rating | E13: =IFERROR(__xludf.DUMMYFUNCTION("SINGLE(IMAGE(E14))"),"") | F13: =IFERROR(__xludf.DUMMYFUNCTION("SINGLE(IMAGE(F14))"),"") | G13: =IFERROR(__xludf.DUMMYFUNCTION("SINGLE(IMAGE(G14))"),"") | H13: =IFERROR(__xludf.DUMMYFUNCTION("SINGLE(IMAGE(H14))"),"") | I13: =IFERROR(__xludf.DUMMYFUNCTION("SINGLE(IMAGE(I14))"),"") | J13: =IFERROR(__xludf.DUMMYFUNCTION("SINGLE(IMAGE(J14))"),"") | K13: =IFERROR(__xludf.DUMMYFUNCTION("SINGLE(IMAGE(K14))"),"") | L13: =IFERROR(__xludf.DUMMYFUNCTION("SINGLE(IMAGE(L14))"),"") | M13: =IFERROR(__xludf.DUMMYFUNCTION("SINGLE(IMAGE(M14))"),"") | N13: =IFERROR(__xludf.DUMMYFUNCTION("SINGLE(IMAGE(N14))"),"")
C14: Review Count | E14: =IFERROR(__xludf.DUMMYFUNCTION("SINGLE(IMAGE(E15))"),"") | F14: =IFERROR(__xludf.DUMMYFUNCTION("SINGLE(IMAGE(F15))"),"") | G14: =IFERROR(__xludf.DUMMYFUNCTION("SINGLE(IMAGE(G15))"),"") | H14: =IFERROR(__xludf.DUMMYFUNCTION("SINGLE(IMAGE(H15))"),"") | I14: =IFERROR(__xludf.DUMMYFUNCTION("SINGLE(IMAGE(I15))"),"") | J14: =IFERROR(__xludf.DUMMYFUNCTION("SINGLE(IMAGE(J15))"),"") | K14: =IFERROR(__xludf.DUMMYFUNCTION("SINGLE(IMAGE(K15))"),"") | L14: =IFERROR(__xludf.DUMMYFUNCTION("SINGLE(IMAGE(L15))"),"") | M14: =IFERROR(__xludf.DUMMYFUNCTION("SINGLE(IMAGE(M15))"),"") | N14: =IFERROR(__xludf.DUMMYFUNCTION("SINGLE(IMAGE(N15))"),"")
C15: Review Velocity | E15: =IFERROR(__xludf.DUMMYFUNCTION("SINGLE(IMAGE(E16))"),"") | F15: =IFERROR(__xludf.DUMMYFUNCTION("SINGLE(IMAGE(F16))"),"") | G15: =IFERROR(__xludf.DUMMYFUNCTION("SINGLE(IMAGE(G16))"),"") | H15: =IFERROR(__xludf.DUMMYFUNCTION("SINGLE(IMAGE(H16))"),"") | I15: =IFERROR(__xludf.DUMMYFUNCTION("SINGLE(IMAGE(I16))"),"") | J15: =IFERROR(__xludf.DUMMYFUNCTION("SINGLE(IMAGE(J16))"),"") | K15: =IFERROR(__xludf.DUMMYFUNCTION("SINGLE(IMAGE(K16))"),"") | L15: =IFERROR(__xludf.DUMMYFUNCTION("SINGLE(IMAGE(L16))"),"") | M15: =IFERROR(__xludf.DUMMYFUNCTION("SINGLE(IMAGE(M16))"),"") | N15: =IFERROR(__xludf.DUMMYFUNCTION("SINGLE(IMAGE(N16))"),"")

Sheet Product Opportunity Explorer
B1: Country | C1: USA
B3: Customer Need
B4: golf swing trainer
B5: golf practice
B6: golf accessories for men
B7: golf accessories kit
B8: golf accessories for women
B9: golfing gifts for men
B10: golf gifts for women
B20: Product Opportunity Explorer Data
P21: =ROUND(E21/12,0)
B22: Customer Need | C22: Search Term | D22: Selected? (Y/N/Competitor/Brand) | E22: Search Volume (Past 360 days) | F22: Search Volume Growth (90 days) | G22: Search Volume Growth (180 days) | H22: Click Share (360 days) | I22: Search Conversion Rate (360 days) | J22: Top Clicked Product 1 (Title) | K22: Top Clicked Product 1 (Asin) | L22: Top Clicked Product 2 (Title) | M22: Top Clicked Product 2 (Asin) | N22: Top Clicked Product 3 (Title) | O22: Top Clicked Product 3 (Asin) | P22: Search Volume (Past 30 days) | Q22: Selected?

Sheet Helium10 Reverse ASIN Search
A1: Country | B1: USA
A3: Reverse ASIN Lookup ASIN List
A4: B005SI5PWM
A5: B0DS2DX2GT
A6: B0D3K9F5WZ
A7: B07FCK63SH
A8: B07YMJ7ZPM
A9: B07YYP9KXX
A15: Keyword Phrase | B15: ABA Total Click Share | C15: ABA Total Conv. Share | D15: Selected? (Y/N/Brand/Copetitor) | E15: Keyword Sales | F15: Cerebro IQ Score | G15: Search Volume | H15: Search Volume Trend | I15: H10 PPC Sugg. Bid | J15: H10 PPC Sugg. Min Bid | K15: H10 PPC Sugg. Max Bid | L15: Sponsored ASINs | M15: Competing Products | N15: CPR | O15: Title Density | P15: Amazon Recommended | Q15: Sponsored | R15: Organic | S15: Sponsored Rank (avg) | T15: Sponsored Rank (count) | U15: Amazon Recommended Rank (avg) | V15: Amazon Recommended Rank (count) | W15: Position (Rank) | X15: Relative Rank | Y15: Competitor Rank (avg) | Z15: Ranking Competitors (count) | AA15: Competitor Performance Score | AB15: B0DS2DX2GT | AC15: B0D3K9F5WZ | AD15: B07FCK63SH | AE15: B07YMJ7ZPM | AF15: B07YYP9KXX

Sheet Search Term Report
A1: DE
A2: Adlabs > Search Terms & Targeting > Search Term > Time Period = All Time > Profile = Be Right Golf > Orders is Min 1
A6: Search Term | B6: Selected? (Y/N/Brand/Competitor) | C6: Actively Targeted | D6: Harvested | E6: Negated | F6: Target | G6: Target Type | H6: Campaign Ad Type | I6: Bid | J6: Match Type | K6: Campaign | L6: Last 30d Sales | M6: Last 30d Spend | N6: Spend | O6: Sales | P6: Clicks | Q6: ACOS | R6: CVR | S6: CPC | T6: Impressions | U6: Orders | V6: Units | W6: Same SKU Orders | X6: Same SKU Sales | Y6: Other SKU Sales | Z6: CTR

Sheet BA TST - Golf
A1: Country | B1: USA | G1: Country | H1: USA | J1: Country | K1: USA | M1: Country | N1: USA | P1: Country | Q1: USA | S1: Country | T1: USA
A2: Reporting Range | B2: Monthly | G2: Reporting Range | H2: Monthly | J2: Reporting Range | K2: Monthly | M2: Reporting Range | N2: Monthly | P2: Reporting Range | Q2: Monthly | S2: Reporting Range | T2: Monthly
A3: Select Year | B3: 2026 | G3: Select Year | H3: 2026 | J3: Select Year | K3: 2026 | M3: Select Year | N3: 2026 | P3: Select Year | Q3: 2026 | S3: Select Year | T3: 2026
A4: Select Month | B4: January | G4: Select Month | H4: January | J4: Select Month | K4: January | M4: Select Month | N4: January | P4: Select Month | Q4: January | S4: Select Month | T4: January
A5: Search Term Filter Word | B5: Golf | G5: Search Term Filter Word | H5: Swing | J5: Search Term Filter Word | K5: Putting | M5: Search Term Filter Word | N5: Trainer | P5: Search Term Filter Word | Q5: Accessories | S5: Search Term Filter Word | T5: golfing
A8: Reporting Range=["Monthly"] | B8: Select year=["2026"] | D8: Select month=["January"] | E8: Search Term=["Golf"]
A9: Search Frequency Rank | B9: Search Term | C9: Select (Y/N) | D9: Top Clicked Brand #1 | E9: Top Clicked Brands #2 | F9: Top Clicked Brands #3 | G9: Top Clicked Category #1 | H9: Top Clicked Category #2 | I9: Top Clicked Category #3 | J9: Top Clicked Product #1: ASIN | K9: Top Clicked Product #1: Product Title | L9: Top Clicked Product #1: Click Share | M9: Top Clicked Product #1: Conversion Share | N9: Top Clicked Product #2: ASIN | O9: Top Clicked Product #2: Product Title | P9: Top Clicked Product #2: Click Share | Q9: Top Clicked Product #2: Conversion Share | R9: Top Clicked Product #3: ASIN | S9: Top Clicked Product #3: Product Title | T9: Top Clicked Product #3: Click Share | U9: Top Clicked Product #3: Conversion Share | V9: Reporting Date

Sheet BA TST - Swing
A1: Country | B1: USA | G1: Country | H1: USA | J1: Country | K1: USA | M1: Country | N1: USA | P1: Country | Q1: USA | S1: Country | T1: USA
A2: Reporting Range | B2: Monthly | G2: Reporting Range | H2: Monthly | J2: Reporting Range | K2: Monthly | M2: Reporting Range | N2: Monthly | P2: Reporting Range | Q2: Monthly | S2: Reporting Range | T2: Monthly
A3: Select Year | B3: 2026 | G3: Select Year | H3: 2026 | J3: Select Year | K3: 2026 | M3: Select Year | N3: 2026 | P3: Select Year | Q3: 2026 | S3: Select Year | T3: 2026
A4: Select Month | B4: January | G4: Select Month | H4: January | J4: Select Month | K4: January | M4: Select Month | N4: January | P4: Select Month | Q4: January | S4: Select Month | T4: January
A5: Search Term Filter Word | B5: Golf | G5: Search Term Filter Word | H5: Swing | J5: Search Term Filter Word | K5: Putting | M5: Search Term Filter Word | N5: Trainer | P5: Search Term Filter Word | Q5: Accessories | S5: Search Term Filter Word | T5: golfing
A8: Reporting Range=["Monthly"] | B8: Select year=["2026"] | D8: Select month=["January"] | E8: Search Term=["Swing"]
A9: Search Frequency Rank | B9: Search Term | C9: Selecte (Y/N) | D9: Top Clicked Brand #1 | E9: Top Clicked Brands #2 | F9: Top Clicked Brands #3 | G9: Top Clicked Category #1 | H9: Top Clicked Category #2 | I9: Top Clicked Category #3 | J9: Top Clicked Product #1: ASIN | K9: Top Clicked Product #1: Product Title | L9: Top Clicked Product #1: Click Share | M9: Top Clicked Product #1: Conversion Share | N9: Top Clicked Product #2: ASIN | O9: Top Clicked Product #2: Product Title | P9: Top Clicked Product #2: Click Share | Q9: Top Clicked Product #2: Conversion Share | R9: Top Clicked Product #3: ASIN | S9: Top Clicked Product #3: Product Title | T9: Top Clicked Product #3: Click Share | U9: Top Clicked Product #3: Conversion Share | V9: Reporting Date

Sheet BA TST - Putting 
A1: Country | B1: USA | G1: Country | H1: USA | J1: Country | K1: USA | M1: Country | N1: USA | P1: Country | Q1: USA | S1: Country | T1: USA
A2: Reporting Range | B2: Monthly | G2: Reporting Range | H2: Monthly | J2: Reporting Range | K2: Monthly | M2: Reporting Range | N2: Monthly | P2: Reporting Range | Q2: Monthly | S2: Reporting Range | T2: Monthly
A3: Select Year | B3: 2026 | G3: Select Year | H3: 2026 | J3: Select Year | K3: 2026 | M3: Select Year | N3: 2026 | P3: Select Year | Q3: 2026 | S3: Select Year | T3: 2026
A4: Select Month | B4: January | G4: Select Month | H4: January | J4: Select Month | K4: January | M4: Select Month | N4: January | P4: Select Month | Q4: January | S4: Select Month | T4: January
A5: Search Term Filter Word | B5: Golf | G5: Search Term Filter Word | H5: Swing | J5: Search Term Filter Word | K5: Putting | M5: Search Term Filter Word | N5: Trainer | P5: Search Term Filter Word | Q5: Accessories | S5: Search Term Filter Word | T5: golfing
A8: Reporting Range=["Monthly"] | B8: Select year=["2026"] | D8: Select month=["January"] | E8: Search Term=["Putting "]
A9: Search Frequency Rank | B9: Search Term | C9: Selecte (Y/N) | D9: Top Clicked Brand #1 | E9: Top Clicked Brands #2 | F9: Top Clicked Brands #3 | G9: Top Clicked Category #1 | H9: Top Clicked Category #2 | I9: Top Clicked Category #3 | J9: Top Clicked Product #1: ASIN | K9: Top Clicked Product #1: Product Title | L9: Top Clicked Product #1: Click Share | M9: Top Clicked Product #1: Conversion Share | N9: Top Clicked Product #2: ASIN | O9: Top Clicked Product #2: Product Title | P9: Top Clicked Product #2: Click Share | Q9: Top Clicked Product #2: Conversion Share | R9: Top Clicked Product #3: ASIN | S9: Top Clicked Product #3: Product Title | T9: Top Clicked Product #3: Click Share | U9: Top Clicked Product #3: Conversion Share | V9: Reporting Date | W9: Select (Y/N)

Sheet BA TST -  Trainer
A1: Country | B1: USA | G1: Country | H1: USA | J1: Country | K1: USA | M1: Country | N1: USA | P1: Country | Q1: USA | S1: Country | T1: USA
A2: Reporting Range | B2: Monthly | G2: Reporting Range | H2: Monthly | J2: Reporting Range | K2: Monthly | M2: Reporting Range | N2: Monthly | P2: Reporting Range | Q2: Monthly | S2: Reporting Range | T2: Monthly
A3: Select Year | B3: 2026 | G3: Select Year | H3: 2026 | J3: Select Year | K3: 2026 | M3: Select Year | N3: 2026 | P3: Select Year | Q3: 2026 | S3: Select Year | T3: 2026
A4: Select Month | B4: January | G4: Select Month | H4: January | J4: Select Month | K4: January | M4: Select Month | N4: January | P4: Select Month | Q4: January | S4: Select Month | T4: January
A5: Search Term Filter Word | B5: Golf | G5: Search Term Filter Word | H5: Swing | J5: Search Term Filter Word | K5: Putting | M5: Search Term Filter Word | N5: Trainer | P5: Search Term Filter Word | Q5: Accessories | S5: Search Term Filter Word | T5: golfing
A8: Reporting Range=["Monthly"] | B8: Select year=["2026"] | D8: Select month=["January"] | E8: Search Term=["Trainer"]
A9: Search Frequency Rank | B9: Search Term | C9: Select (Y/N) | D9: Top Clicked Brand #1 | E9: Top Clicked Brands #2 | F9: Top Clicked Brands #3 | G9: Top Clicked Category #1 | H9: Top Clicked Category #2 | I9: Top Clicked Category #3 | J9: Top Clicked Product #1: ASIN | K9: Top Clicked Product #1: Product Title | L9: Top Clicked Product #1: Click Share | M9: Top Clicked Product #1: Conversion Share | N9: Top Clicked Product #2: ASIN | O9: Top Clicked Product #2: Product Title | P9: Top Clicked Product #2: Click Share | Q9: Top Clicked Product #2: Conversion Share | R9: Top Clicked Product #3: ASIN | S9: Top Clicked Product #3: Product Title | T9: Top Clicked Product #3: Click Share | U9: Top Clicked Product #3: Conversion Share | V9: Reporting Date

Sheet BA TST - Accessories
A1: Country | B1: USA | G1: Country | H1: USA | J1: Country | K1: USA | M1: Country | N1: USA | P1: Country | Q1: USA | S1: Country | T1: USA
A2: Reporting Range | B2: Monthly | G2: Reporting Range | H2: Monthly | J2: Reporting Range | K2: Monthly | M2: Reporting Range | N2: Monthly | P2: Reporting Range | Q2: Monthly | S2: Reporting Range | T2: Monthly
A3: Select Year | B3: 2026 | G3: Select Year | H3: 2026 | J3: Select Year | K3: 2026 | M3: Select Year | N3: 2026 | P3: Select Year | Q3: 2026 | S3: Select Year | T3: 2026
A4: Select Month | B4: January | G4: Select Month | H4: January | J4: Select Month | K4: January | M4: Select Month | N4: January | P4: Select Month | Q4: January | S4: Select Month | T4: January
A5: Search Term Filter Word | B5: Golf | G5: Search Term Filter Word | H5: Swing | J5: Search Term Filter Word | K5: Putting | M5: Search Term Filter Word | N5: Trainer | P5: Search Term Filter Word | Q5: Accessories | S5: Search Term Filter Word | T5: golfing
A8: Reporting Range=["Monthly"] | B8: Select year=["2026"] | D8: Select month=["January"] | E8: Search Term=["Accessories"]
A9: Search Frequency Rank | B9: Search Term | C9: Select (Y/N) | D9: Top Clicked Brand #1 | E9: Top Clicked Brands #2 | F9: Top Clicked Brands #3 | G9: Top Clicked Category #1 | H9: Top Clicked Category #2 | I9: Top Clicked Category #3 | J9: Top Clicked Product #1: ASIN | K9: Top Clicked Product #1: Product Title | L9: Top Clicked Product #1: Click Share | M9: Top Clicked Product #1: Conversion Share | N9: Top Clicked Product #2: ASIN | O9: Top Clicked Product #2: Product Title | P9: Top Clicked Product #2: Click Share | Q9: Top Clicked Product #2: Conversion Share | R9: Top Clicked Product #3: ASIN | S9: Top Clicked Product #3: Product Title | T9: Top Clicked Product #3: Click Share | U9: Top Clicked Product #3: Conversion Share | V9: Reporting Date

Sheet BA TST - golfinggolfing
A1: Country | B1: USA | G1: Country | H1: USA | J1: Country | K1: USA | M1: Country | N1: USA | P1: Country | Q1: USA | S1: Country | T1: USA
A2: Reporting Range | B2: Monthly | G2: Reporting Range | H2: Monthly | J2: Reporting Range | K2: Monthly | M2: Reporting Range | N2: Monthly | P2: Reporting Range | Q2: Monthly | S2: Reporting Range | T2: Monthly
A3: Select Year | B3: 2026 | G3: Select Year | H3: 2026 | J3: Select Year | K3: 2026 | M3: Select Year | N3: 2026 | P3: Select Year | Q3: 2026 | S3: Select Year | T3: 2026
A4: Select Month | B4: January | G4: Select Month | H4: January | J4: Select Month | K4: January | M4: Select Month | N4: January | P4: Select Month | Q4: January | S4: Select Month | T4: January
A5: Search Term Filter Word | B5: Golf | G5: Search Term Filter Word | H5: Swing | J5: Search Term Filter Word | K5: Putting | M5: Search Term Filter Word | N5: Trainer | P5: Search Term Filter Word | Q5: Accessories | S5: Search Term Filter Word | T5: golfing
A8: Reporting Range=["Monthly"] | B8: Select year=["2026"] | D8: Select month=["January"] | E8: Search Term=["golfing"]
A9: Search Frequency Rank | B9: Search Term | C9: Selecte (Y/N) | D9: Top Clicked Brand #1 | E9: Top Clicked Brands #2 | F9: Top Clicked Brands #3 | G9: Top Clicked Category #1 | H9: Top Clicked Category #2 | I9: Top Clicked Category #3 | J9: Top Clicked Product #1: ASIN | K9: Top Clicked Product #1: Product Title | L9: Top Clicked Product #1: Click Share | M9: Top Clicked Product #1: Conversion Share | N9: Top Clicked Product #2: ASIN | O9: Top Clicked Product #2: Product Title | P9: Top Clicked Product #2: Click Share | Q9: Top Clicked Product #2: Conversion Share | R9: Top Clicked Product #3: ASIN | S9: Top Clicked Product #3: Product Title | T9: Top Clicked Product #3: Click Share | U9: Top Clicked Product #3: Conversion Share | V9: Reporting Date

Sheet Brand Analytics - ASIN Filter
A1: Country | B1: US
A2: Reporting Range | B2: Monthly
A3: Select Year | B3: 2026
A4: Select Month | B4: January
A5: Top clicked products | B5: From Helium10 Reverse ASIN Search
A16: Reporting Range=["Monthly"] | B16: Select year=["2026"] | D16: Select month=["January"] | E16: Top Clicked Products=["B005SI5PWM B0DS2DX2GT B0D3K9F5WZ B07FCK63SH B07YMJ7ZPM B07YYP9KXX"]
A17: Search Frequency Rank | B17: Search Term | C17: Select (Y/N) | D17: Top Clicked Brand #1 | E17: Top Clicked Brands #2 | F17: Top Clicked Brands #3 | G17: Top Clicked Category #1 | H17: Top Clicked Category #2 | I17: Top Clicked Category #3 | J17: Top Clicked Product #1: ASIN | K17: Top Clicked Product #1: Product Title | L17: Top Clicked Product #1: Click Share | M17: Top Clicked Product #1: Conversion Share | N17: Top Clicked Product #2: ASIN | O17: Top Clicked Product #2: Product Title | P17: Top Clicked Product #2: Click Share | Q17: Top Clicked Product #2: Conversion Share | R17: Top Clicked Product #3: ASIN | S17: Top Clicked Product #3: Product Title | T17: Top Clicked Product #3: Click Share | U17: Top Clicked Product #3: Conversion Share | V17: Reporting Date

Sheet SQP Report B0DQV3BZD7
A1: Download from Be Right Golf Store by changing the Country dropdown to US
A2: Country | D2: US
A3: View | D3: ASIN View
A4: ASIN | D4: B0DSY8FV5D
A5: Reporting Range | D5: Monthly
A6: Year | D6: 2026
A7: Month | D7: January
A10: ASIN or Product=["B0DSY8FV5D"] | C10: Reporting Range=["Monthly"] | D10: Select year=["2026"] | E10: Select month=["January"]
A11: Search Query | B11: Select (Y/N/Brand/Competitor) | C11: Search Query Score | D11: Search Query Volume | E11: Impressions: Total Count | F11: Impressions: ASIN Count | G11: Impressions: ASIN Share % | H11: Clicks: Total Count | I11: Clicks: Click Rate % | J11: Clicks: ASIN Count | K11: Clicks: ASIN Share % | L11: Clicks: Price (Median) | M11: Clicks: ASIN Price (Median) | N11: Clicks: Same Day Shipping Speed | O11: Clicks: 1D Shipping Speed | P11: Clicks: 2D Shipping Speed | Q11: Cart Adds: Total Count | R11: Cart Adds: Cart Add Rate % | S11: Cart Adds: ASIN Count | T11: Cart Adds: ASIN Share % | U11: Cart Adds: Price (Median) | V11: Cart Adds: ASIN Price (Median) | W11: Cart Adds: Same Day Shipping Speed | X11: Cart Adds: 1D Shipping Speed | Y11: Cart Adds: 2D Shipping Speed | Z11: Purchases: Total Count | AA11: Purchases: Purchase Rate % | AB11: Purchases: ASIN Count | AC11: Purchases: ASIN Share % | AD11: Purchases: Price (Median) | AE11: Purchases: ASIN Price (Median) | AF11: Purchases: Same Day Shipping Speed | AG11: Purchases: 1D Shipping Speed | AH11: Purchases: 2D Shipping Speed | AI11: Reporting Date

Sheet Brand
A1: Country | B1: US
A3: Reverse ASIN Lookup ASIN List
A4: B0DSY8FV5D
A6: Keyword Phrase | B6: ABA Total Click Share | C6: ABA Total Conv. Share | D6: Select? (Y/N) | E6: Keyword Sales | F6: Cerebro IQ Score | G6: Search Volume | H6: Search Volume Trend | I6: H10 PPC Sugg. Bid | J6: H10 PPC Sugg. Min Bid | K6: H10 PPC Sugg. Max Bid | L6: Sponsored ASINs | M6: Competing Products | N6: CPR | O6: Title Density | P6: Amazon Recommended | Q6: Sponsored | R6: Organic | S6: Amazon Rec. Rank | T6: Sponsored Rank | U6: Organic Rank
